{"name":"Modification de l\u0027adresse d\u0027un abonné résidant en France sans ou avec date d\u0027effet","id":"modifier-l-adresse-d-un-abonné;modification-de-l-adresse-d-un-abonné-résidant-en-france-sans-ou-avec-date-d-effet","testSteps":[{"number":1,"description":"Example: {canal\u003dFACE}","duration":92,"startTime":"2020-10-30T23:19:39.489+01:00[Africa/Luanda]","exception":{"errorType":"java.lang.IllegalArgumentException","message":"RestTemplate must not be null","stackTrace":[{"declaringClass":"org.springframework.util.Assert","methodName":"notNull","fileName":"Assert.java","lineNumber":201},{"declaringClass":"org.springframework.test.web.client.MockRestServiceServer","methodName":"bindTo","fileName":"MockRestServiceServer.java","lineNumber":133},{"declaringClass":"org.springframework.test.web.client.MockRestServiceServer","methodName":"createServer","fileName":"MockRestServiceServer.java","lineNumber":165},{"declaringClass":"com.testCanal.testCanal.stepDefinition.StepDefinitions","methodName":"setup","fileName":"StepDefinitions.java","lineNumber":55}]},"result":"ERROR","precondition":false,"level":0,"lineNumber":11,"children":[{"number":2,"description":"Etant donné un abonné avec une adresse principale \"\u003cactive\u003e\" en France","duration":6,"startTime":"2020-10-30T23:19:39.547+01:00[Africa/Luanda]","result":"IGNORED","precondition":false,"level":1},{"number":3,"description":"Lorsque le conseiller connecté à \"FACE\" modifie l\u0027adresse de l\u0027abonné","duration":2,"startTime":"2020-10-30T23:19:39.558+01:00[Africa/Luanda]","result":"IGNORED","precondition":false,"level":1},{"number":4,"description":"Alors l\u0027adresse de l\u0027abonné modifiée est enregistrée sur l\u0027ensemble des contrats de l\u0027abonné","duration":1,"startTime":"2020-10-30T23:19:39.561+01:00[Africa/Luanda]","result":"IGNORED","precondition":false,"level":1},{"number":5,"description":"Et un mouvement de modification d\u0027adresse est créé","duration":2,"startTime":"2020-10-30T23:19:39.563+01:00[Africa/Luanda]","result":"IGNORED","precondition":false,"level":1}]},{"number":6,"description":"Example: {canal\u003dEC}","duration":28,"startTime":"2020-10-30T23:19:39.659+01:00[Africa/Luanda]","exception":{"errorType":"java.lang.IllegalArgumentException","message":"RestTemplate must not be null","stackTrace":[{"declaringClass":"org.springframework.util.Assert","methodName":"notNull","fileName":"Assert.java","lineNumber":201},{"declaringClass":"org.springframework.test.web.client.MockRestServiceServer","methodName":"bindTo","fileName":"MockRestServiceServer.java","lineNumber":133},{"declaringClass":"org.springframework.test.web.client.MockRestServiceServer","methodName":"createServer","fileName":"MockRestServiceServer.java","lineNumber":165},{"declaringClass":"com.testCanal.testCanal.stepDefinition.StepDefinitions","methodName":"setup","fileName":"StepDefinitions.java","lineNumber":55}]},"result":"ERROR","precondition":false,"level":0,"lineNumber":12,"children":[{"number":7,"description":"Etant donné un abonné avec une adresse principale \"\u003cactive\u003e\" en France","duration":2,"startTime":"2020-10-30T23:19:39.663+01:00[Africa/Luanda]","result":"SKIPPED","precondition":false,"level":1},{"number":8,"description":"Lorsque le conseiller connecté à \"EC\" modifie l\u0027adresse de l\u0027abonné","duration":2,"startTime":"2020-10-30T23:19:39.666+01:00[Africa/Luanda]","result":"SKIPPED","precondition":false,"level":1},{"number":9,"description":"Alors l\u0027adresse de l\u0027abonné modifiée est enregistrée sur l\u0027ensemble des contrats de l\u0027abonné","duration":7,"startTime":"2020-10-30T23:19:39.669+01:00[Africa/Luanda]","result":"SKIPPED","precondition":false,"level":1},{"number":10,"description":"Et un mouvement de modification d\u0027adresse est créé","duration":3,"startTime":"2020-10-30T23:19:39.678+01:00[Africa/Luanda]","result":"SKIPPED","precondition":false,"level":1}]}],"userStory":{"id":"modifier-l-adresse-d-un-abonné","storyName":"Modifier l\u0027adresse d\u0027un abonné","path":"file:///C:/Logiciels/test/testCanal1/testCanal/src/test/resources/features/adresse.feature","type":"feature"},"featureTag":{"name":"Modifier l\u0027adresse d\u0027un abonné","type":"feature","displayName":"Modifier l\u0027adresse d\u0027un abonné"},"title":"Modification de l\u0027adresse d\u0027un abonné résidant en France sans ou avec date d\u0027effet","description":"","tags":[{"name":"modification","type":"tag","displayName":"modification"},{"name":"adresse","type":"tag","displayName":"adresse"}],"startTime":"2020-10-30T23:19:39.391+01:00[Africa/Luanda]","duration":297,"testFailureCause":{"errorType":"java.lang.IllegalArgumentException","message":"RestTemplate must not be null","stackTrace":[{"declaringClass":"org.springframework.util.Assert","methodName":"notNull","fileName":"Assert.java","lineNumber":201},{"declaringClass":"org.springframework.test.web.client.MockRestServiceServer","methodName":"bindTo","fileName":"MockRestServiceServer.java","lineNumber":133},{"declaringClass":"org.springframework.test.web.client.MockRestServiceServer","methodName":"createServer","fileName":"MockRestServiceServer.java","lineNumber":165},{"declaringClass":"com.testCanal.testCanal.stepDefinition.StepDefinitions","methodName":"setup","fileName":"StepDefinitions.java","lineNumber":55}]},"testFailureClassname":"java.lang.IllegalArgumentException","testFailureMessage":"RestTemplate must not be null","testFailureSummary":"ERROR;java.lang.IllegalArgumentException;RestTemplate must not be null;Assert.java","projectKey":"","isManualTestingUpToDate":false,"dataTable":{"headers":["canal"],"rows":[{"values":["FACE"],"lineNumber":11,"result":"ERROR"},{"values":["EC"],"lineNumber":12,"result":"ERROR"}],"predefinedRows":true,"scenarioOutline":"Etant donné un abonné avec une adresse principale \"\u003cactive\u003e\" en France\n\rLorsque le conseiller connecté à \"\u003ccanal\u003e\" modifie l\u0027adresse de l\u0027abonné\n\rAlors l\u0027adresse de l\u0027abonné modifiée est enregistrée sur l\u0027ensemble des contrats de l\u0027abonné\n\rEt un mouvement de modification d\u0027adresse est créé\n\r","dataSetDescriptors":[{"startRow":0,"rowCount":0,"name":"","description":""}]},"manual":false,"testSource":"Cucumber","result":"ERROR","scenarioOutline":"Etant donné un abonné avec une adresse principale \"\u003cactive\u003e\" en France\r\nLorsque le conseiller connecté à \"\u003ccanal\u003e\" modifie l\u0027adresse de l\u0027abonné\r\nAlors l\u0027adresse de l\u0027abonné modifiée est enregistrée sur l\u0027ensemble des contrats de l\u0027abonné\r\nEt un mouvement de modification d\u0027adresse est créé"}